connector/__init__.py
connector/api.py
fringe_connector/__init__.py
fringe_connector/api.py
fringe_utils/__init__.py
fringe_utils/utils.py
fringe_web_driver/__init__.py
fringe_web_driver/selenium.py
insomnyak_connector/__init__.py
insomnyak_connector/api.py
utils/__init__.py
utils/utils.py
fringe_connector-0.0.110.dist-info/LICENSE
fringe_connector-0.0.110.dist-info/METADATA
fringe_connector-0.0.110.dist-info/WHEEL
fringe_connector-0.0.110.dist-info/top_level.txt
fringe_connector-0.0.110.dist-info/RECORD
