Metadata-Version: 2.1
Name: fringe-connector
Version: 0.0.110
Summary: Suite of prebuilt connectors to other APIs
Home-page: https://pypi.org/project/insomnyak-connector/
Author: Rene Serulle
Author-email: rene@insomnyak.com
Keywords: gcp gsuite gmail gsheets bigquery gdrive
Classifier: Programming Language :: Python :: 3
Classifier: License :: OSI Approved :: Apache Software License
Classifier: Operating System :: OS Independent
Classifier: Development Status :: 3 - Alpha
Requires-Python: >=3.7.3
License-File: LICENSE
Requires-Dist: numpy
Requires-Dist: pandas
Requires-Dist: google-api-python-client
Requires-Dist: google-auth-httplib2
Requires-Dist: google-auth-oauthlib
Requires-Dist: google-cloud-storage
Requires-Dist: google-cloud-bigquery ==1.25.0
Requires-Dist: google-cloud-bigquery-storage ==1.0.0
Requires-Dist: selenium
